warriorwapp/__init__.py
warriorwapp/Actions/__init__.py
warriorwapp/Actions/WappActions/__init__.py
warriorwapp/Actions/WappActions/WappReportingActions/__init__.py
warriorwapp/Actions/WappActions/WappReportingActions/wapp_reporting_actions.py
warriorwapp/ProductDrivers/__init__.py
warriorwapp/ProductDrivers/wapp_driver.py
warriorwapp-1.0.0.dist-info/METADATA
warriorwapp-1.0.0.dist-info/WHEEL
warriorwapp-1.0.0.dist-info/top_level.txt
warriorwapp-1.0.0.dist-info/RECORD
